{
  "finishers": [
    {
      "date": "2025-01-15",
      "category": "gold",
      "name": "Max Mustermann",
      "route": "Slateman Hunsrück-Soonwald",
      "activityLink": "https://www.strava.com/activities/123456789",
      "platform": "strava"
    },
    {
      "date": "2025-01-20",
      "category": "silver", 
      "name": "Erika Mustermann",
      "route": "Slateman Hunsrück-Hochwald",
      "activityLink": "https://www.komoot.com/de-de/tour/123456789",
      "platform": "komoot"
    }
  ]
} 